<?xml version="1.0" encoding="ISO-8859-1"?>
<!-- XML generated by UTFXML Version 2.2 built 19-Aug-2010 -->
<UTFXML filename="cfdkstation2.cmp" path="BASES\BRETONIA">
   <UTF_ROOT>
      <VMeshLibrary>
         <ord-detaljcici.tga.lod0.vms include="cfdkstation2_cmp\lod0.vms.xml"/>
      </VMeshLibrary>
      <Cmpnd>
         <Root>
            <File_name name="File name" type="text">ord-detaljcici.tga.3db</File_name>
            <Index type="int">0</Index>
            <Object_name name="Object name" type="text">Root</Object_name>
         </Root>
      </Cmpnd>
      <ord-detaljcici.tga.3db>
         <Hardpoints>
            <Fixed>
               <HpLightA01>
                  <Position type="Vector">4.5644531, -8, -11.940086</Position>
                  <Orientation type="Matrix">
                      -0.9999994000, -1.5258586e-09, -87.414563e-09,
                      87.427878e-09,  -0.0174524780,  -0.9998473500,
                       0.0000000000,  -0.9998473500,   0.0174530740
                  </Orientation>
               </HpLightA01>
               <HpLightA02>
                  <Position type="Vector">-4.5, -8, -11.9</Position>
                  <Orientation type="Matrix">
                      -0.9999994000, -1.5258586e-09, -87.414563e-09,
                      87.427878e-09,  -0.0174524780,  -0.9998473500,
                       0.0000000000,  -0.9998473500,   0.0174530740
                  </Orientation>
               </HpLightA02>
               <HpLightB01>
                  <Position type="Vector">0, -13, -11.5</Position>
                  <Orientation type="Matrix">
                      -0.9999994000, -1.5258586e-09, -87.414563e-09,
                      87.427878e-09,  -0.0174524780,  -0.9998473500,
                       0.0000000000,  -0.9998473500,   0.0174530740
                  </Orientation>
               </HpLightB01>
               <HpLightB02>
                  <Position type="Vector">0, -13, 11</Position>
                  <Orientation type="Matrix">
                      -0.9999994000, -1.5258586e-09, -87.414563e-09,
                      87.427878e-09,  -0.0174524780,  -0.9998473500,
                       0.0000000000,  -0.9998473500,   0.0174530740
                  </Orientation>
               </HpLightB02>
               <HpLightB03>
                  <Position type="Vector">-8, -13, -8</Position>
                  <Orientation type="Matrix">
                      -0.9999994000, -1.5258586e-09, -87.414563e-09,
                      87.427878e-09,  -0.0174524780,  -0.9998473500,
                       0.0000000000,  -0.9998473500,   0.0174530740
                  </Orientation>
               </HpLightB03>
               <HpLightB04>
                  <Position type="Vector">8, -13, 8</Position>
                  <Orientation type="Matrix">
                      -0.9999994000, -1.5258586e-09, -87.414563e-09,
                      87.427878e-09,  -0.0174524780,  -0.9998473500,
                       0.0000000000,  -0.9998473500,   0.0174530740
                  </Orientation>
               </HpLightB04>
               <HpLightB05>
                  <Position type="Vector">8, -13, -8</Position>
                  <Orientation type="Matrix">
                      -0.9999994000, -1.5258586e-09, -87.414563e-09,
                      87.427878e-09,  -0.0174524780,  -0.9998473500,
                       0.0000000000,  -0.9998473500,   0.0174530740
                  </Orientation>
               </HpLightB05>
               <HpLightB06>
                  <Position type="Vector">-8, -13, 8</Position>
                  <Orientation type="Matrix">
                      -0.9999994000, -1.5258586e-09, -87.414563e-09,
                      87.427878e-09,  -0.0174524780,  -0.9998473500,
                       0.0000000000,  -0.9998473500,   0.0174530740
                  </Orientation>
               </HpLightB06>
               <HpLightB07>
                  <Position type="Vector">11, -13, 0</Position>
                  <Orientation type="Matrix">
                      -0.9999994000, -1.5258586e-09, -87.414563e-09,
                      87.427878e-09,  -0.0174524780,  -0.9998473500,
                       0.0000000000,  -0.9998473500,   0.0174530740
                  </Orientation>
               </HpLightB07>
               <HpLightB08>
                  <Position type="Vector">-11, -13, 0</Position>
                  <Orientation type="Matrix">
                      -0.9999994000, -1.5258586e-09, -87.414563e-09,
                      87.427878e-09,  -0.0174524780,  -0.9998473500,
                       0.0000000000,  -0.9998473500,   0.0174530740
                  </Orientation>
               </HpLightB08>
               <HpLightA03>
                  <Orientation type="Matrix">
                       1.0000000000,   0.0000000000,   0.0000000000,
                       0.0000000000,   1.0000000000,   0.0000000000,
                       0.0000000000,   0.0000000000,   1.0000000000
                  </Orientation>
                  <Position type="Vector">-21.307144, -13, -28.08367</Position>
               </HpLightA03>
               <HpLightA04>
                  <Orientation type="Matrix">
                       1.0000000000,   0.0000000000,   0.0000000000,
                       0.0000000000,   1.0000000000,   0.0000000000,
                       0.0000000000,   0.0000000000,   1.0000000000
                  </Orientation>
                  <Position type="Vector">21.064081, -13, -28.852695</Position>
               </HpLightA04>
            </Fixed>
         </Hardpoints>
         <VMeshPart>
            <VMeshRef type="VMeshRef">
               <!-- header size  --> 60,
               <!-- vmesh lib    --> ord-detaljcici.tga.lod0.vms,
               <!-- start vert   --> 0,
               <!-- num verts    --> 11918,
               <!-- start index  --> 0,
               <!-- num indices  --> 22374,
               <!-- start mesh   --> 0,
               <!-- num meshes   --> 7,
               <!-- bounding box -->  143.56471,  183.28722,   227.53226,
                                     -143.56471, -151.08633,  -131.68008,
               <!-- center       -->    0,         16.100441,   47.926086,
               <!-- radius       --> 406.92438
            </VMeshRef>
         </VMeshPart>
      </ord-detaljcici.tga.3db>
      <Material_library name="Material library">
         <ord-detaljcici.tga>
            <Dt_flags type="int">0x40</Dt_flags>
            <Dt_name type="text">ord-detaljcici.tga.tga</Dt_name>
            <Type type="text">DcDt</Type>
         </ord-detaljcici.tga>
         <ord-podloga.tga>
            <Dt_flags type="int">0x40</Dt_flags>
            <Dt_name type="text">ord-podloga.tga.tga</Dt_name>
            <Type type="text">DcDt</Type>
         </ord-podloga.tga>
         <ord-ivicnjaci.tga>
            <Dt_flags type="int">0x40</Dt_flags>
            <Dt_name type="text">ord-ivicnjaci.tga.tga</Dt_name>
            <Type type="text">DcDt</Type>
         </ord-ivicnjaci.tga>
         <ord-mala-svijetla.tga>
            <Dt_flags type="int">0x40</Dt_flags>
            <Dt_name type="text">ord-mala-svijetla.tga.tga</Dt_name>
            <Type type="text">DcDt</Type>
         </ord-mala-svijetla.tga>
         <ord-ivicnjaci-jos.tga>
            <Dt_flags type="int">0x40</Dt_flags>
            <Dt_name type="text">ord-ivicnjaci-jos.tga.tga</Dt_name>
            <Type type="text">DcDt</Type>
         </ord-ivicnjaci-jos.tga>
         <ord-podloga-crveno.tga>
            <Dt_flags type="int">0x40</Dt_flags>
            <Dt_name type="text">ord-podloga-crveno.tga.tga</Dt_name>
            <Type type="text">DcDt</Type>
         </ord-podloga-crveno.tga>
         <ord-prozorcici.tga>
            <Dt_flags type="int">0x40</Dt_flags>
            <Dt_name type="text">ord-prozorcici.tga.tga</Dt_name>
            <Type type="text">DcDt</Type>
         </ord-prozorcici.tga>
         <Material_count name="Material count" type="int">7</Material_count>
      </Material_library>
      <Texture_library name="Texture library">
         <ord-detaljcici.tga.tga>
            <MIPS type="file" filename="cfdkstation2_cmp\ord-detaljcici.tga.dds"/>
         </ord-detaljcici.tga.tga>
         <ord-podloga.tga.tga>
            <MIPS type="file" filename="cfdkstation2_cmp\ord-podloga.tga.dds"/>
         </ord-podloga.tga.tga>
         <ord-ivicnjaci.tga.tga>
            <MIPS type="file" filename="cfdkstation2_cmp\ord-ivicnjaci.tga.dds"/>
         </ord-ivicnjaci.tga.tga>
         <ord-mala-svijetla.tga.tga>
            <MIPS type="file" filename="cfdkstation2_cmp\ord-mala-svijetla.tga.dds"/>
         </ord-mala-svijetla.tga.tga>
         <ord-ivicnjaci-jos.tga.tga>
            <MIPS type="file" filename="cfdkstation2_cmp\ord-ivicnjaci-jos.tga.dds"/>
         </ord-ivicnjaci-jos.tga.tga>
         <ord-podloga-crveno.tga.tga>
            <MIPS type="file" filename="cfdkstation2_cmp\ord-podloga-crveno.tga.dds"/>
         </ord-podloga-crveno.tga.tga>
         <ord-prozorcici.tga.tga>
            <MIPS type="file" filename="cfdkstation2_cmp\ord-prozorcici.tga.dds"/>
         </ord-prozorcici.tga.tga>
      </Texture_library>
   </UTF_ROOT>
</UTFXML>
