<?xml version="1.0" encoding="ISO-8859-1"?>
<!-- XML generated by UTFXML Version 2.2 built 19-Aug-2010 -->
<UTFXML filename="Rebel_Galaxy_ship66.cmp" path="SHIPS\new\Rebel_Galaxy">
   <UTF_ROOT>
      <VMeshLibrary>
         <Rebel_Galaxy_ship66.lod0.vms include="Rebel_Galaxy_ship66_cmp\lod0.vms.xml"/>
      </VMeshLibrary>
      <Cmpnd>
         <Root>
            <File_name name="File name" type="text">Rebel_Galaxy_ship66.3db</File_name>
            <Index type="int">0</Index>
            <Object_name name="Object name" type="text">Root</Object_name>
         </Root>
      </Cmpnd>
      <Rebel_Galaxy_ship66.3db>
         <Hardpoints>
            <Fixed>
               <HpMount>
                  <Orientation type="Matrix">
                       1.0000000000,   0.0000000000,   0.0000000000,
                       0.0000000000,   1.0000000000,   0.0000000000,
                       0.0000000000,   0.0000000000,   1.0000000000
                  </Orientation>
                  <Position type="Vector">0, -40, -50</Position>
               </HpMount>
               <HpBayDoor01>
                  <Orientation type="Matrix">
                       1.0000000000,   0.0000000000,   0.0000000000,
                       0.0000000000,   1.0000000000,   0.0000000000,
                       0.0000000000,   0.0000000000,   1.0000000000
                  </Orientation>
                  <Position type="Vector">0, -45, 0</Position>
               </HpBayDoor01>
               <HpBayDoor02>
                  <Orientation type="Matrix">
                       1.0000000000,   0.0000000000,   0.0000000000,
                       0.0000000000,   1.0000000000,   0.0000000000,
                       0.0000000000,   0.0000000000,   1.0000000000
                  </Orientation>
                  <Position type="Vector">0, -50, 0</Position>
               </HpBayDoor02>
               <HpTractor_Source>
                  <Orientation type="Matrix">
                       1.0000000000,   0.0000000000,   0.0000000000,
                       0.0000000000,   1.0000000000,   0.0000000000,
                       0.0000000000,   0.0000000000,   1.0000000000
                  </Orientation>
                  <Position type="Vector">0, -13.615871, -132.30682</Position>
               </HpTractor_Source>
               <HpCloak01>
                  <Orientation type="Matrix">
                       1.0000000000,   0.0000000000,   0.0000000000,
                       0.0000000000,   1.0000000000,   0.0000000000,
                       0.0000000000,   0.0000000000,   1.0000000000
                  </Orientation>
                  <Position type="Vector">0, 0, 0</Position>
               </HpCloak01>
               <HpFX01>
                  <Orientation type="Matrix">
                       1.0000000000,   0.0000000000,   0.0000000000,
                       0.0000000000,   1.0000000000,   0.0000000000,
                       0.0000000000,   0.0000000000,   1.0000000000
                  </Orientation>
                  <Position type="Vector">0, 0, 0</Position>
               </HpFX01>
               <HpFX02>
                  <Orientation type="Matrix">
                       1.0000000000,   0.0000000000,   0.0000000000,
                       0.0000000000,   1.0000000000,   0.0000000000,
                       0.0000000000,   0.0000000000,   1.0000000000
                  </Orientation>
                  <Position type="Vector">0, 0, 0</Position>
               </HpFX02>
               <HpCM01>
                  <Orientation type="Matrix">
                      -1.0000000000, -71.612547e-09, -50.143644e-09,
                      87.422777e-09,  -0.8191520000,  -0.5735763900,
                       0.0000000000,  -0.5735763900,   0.8191520600
                  </Orientation>
                  <Position type="Vector">0, -12.779292, 71.339668</Position>
               </HpCM01>
               <HpShield01>
                  <Orientation type="Matrix">
                       1.0000000000,   0.0000000000,   0.0000000000,
                       0.0000000000,   1.0000000000,   0.0000000000,
                       0.0000000000,   0.0000000000,   1.0000000000
                  </Orientation>
                  <Position type="Vector">0, 0, 0</Position>
               </HpShield01>
               <HpShield02>
                  <Orientation type="Matrix">
                       1.0000000000,   0.0000000000,   0.0000000000,
                       0.0000000000,   1.0000000000,   0.0000000000,
                       0.0000000000,   0.0000000000,   1.0000000000
                  </Orientation>
                  <Position type="Vector">0, 0, 0</Position>
               </HpShield02>
               <HpShieldGenerator01>
                  <Orientation type="Matrix">
                       1.0000000000,   0.0000000000,   0.0000000000,
                       0.0000000000,   1.0000000000,   0.0000000000,
                       0.0000000000,   0.0000000000,   1.0000000000
                  </Orientation>
                  <Position type="Vector">0, 0, 0</Position>
               </HpShieldGenerator01>
               <HpShieldGenerator02>
                  <Orientation type="Matrix">
                       1.0000000000,   0.0000000000,   0.0000000000,
                       0.0000000000,   1.0000000000,   0.0000000000,
                       0.0000000000,   0.0000000000,   1.0000000000
                  </Orientation>
                  <Position type="Vector">0, 0, 0</Position>
               </HpShieldGenerator02>
               <HpShieldGenerator03>
                  <Orientation type="Matrix">
                       1.0000000000,   0.0000000000,   0.0000000000,
                       0.0000000000,   1.0000000000,   0.0000000000,
                       0.0000000000,   0.0000000000,   1.0000000000
                  </Orientation>
                  <Position type="Vector">0, 0, 0</Position>
               </HpShieldGenerator03>
               <HpShieldGenerator04>
                  <Orientation type="Matrix">
                       1.0000000000,   0.0000000000,   0.0000000000,
                       0.0000000000,   1.0000000000,   0.0000000000,
                       0.0000000000,   0.0000000000,   1.0000000000
                  </Orientation>
                  <Position type="Vector">0, 0, 0</Position>
               </HpShieldGenerator04>
               <HpShieldGenerator05>
                  <Orientation type="Matrix">
                       1.0000000000,   0.0000000000,   0.0000000000,
                       0.0000000000,   1.0000000000,   0.0000000000,
                       0.0000000000,   0.0000000000,   1.0000000000
                  </Orientation>
                  <Position type="Vector">0, 0, 0</Position>
               </HpShieldGenerator05>
               <HpShieldGenerator06>
                  <Orientation type="Matrix">
                       1.0000000000,   0.0000000000,   0.0000000000,
                       0.0000000000,   1.0000000000,   0.0000000000,
                       0.0000000000,   0.0000000000,   1.0000000000
                  </Orientation>
                  <Position type="Vector">0, 0, 0</Position>
               </HpShieldGenerator06>
               <HpShieldCapacity01>
                  <Orientation type="Matrix">
                       1.0000000000,   0.0000000000,   0.0000000000,
                       0.0000000000,   1.0000000000,   0.0000000000,
                       0.0000000000,   0.0000000000,   1.0000000000
                  </Orientation>
                  <Position type="Vector">0, 0, 0</Position>
               </HpShieldCapacity01>
               <HpShieldCapacity02>
                  <Orientation type="Matrix">
                       1.0000000000,   0.0000000000,   0.0000000000,
                       0.0000000000,   1.0000000000,   0.0000000000,
                       0.0000000000,   0.0000000000,   1.0000000000
                  </Orientation>
                  <Position type="Vector">0, 0, 0</Position>
               </HpShieldCapacity02>
               <HpShieldCapacity03>
                  <Orientation type="Matrix">
                       1.0000000000,   0.0000000000,   0.0000000000,
                       0.0000000000,   1.0000000000,   0.0000000000,
                       0.0000000000,   0.0000000000,   1.0000000000
                  </Orientation>
                  <Position type="Vector">0, 0, 0</Position>
               </HpShieldCapacity03>
               <HpShieldCapacity04>
                  <Orientation type="Matrix">
                       1.0000000000,   0.0000000000,   0.0000000000,
                       0.0000000000,   1.0000000000,   0.0000000000,
                       0.0000000000,   0.0000000000,   1.0000000000
                  </Orientation>
                  <Position type="Vector">0, 0, 0</Position>
               </HpShieldCapacity04>
               <HpShieldCapacity05>
                  <Orientation type="Matrix">
                       1.0000000000,   0.0000000000,   0.0000000000,
                       0.0000000000,   1.0000000000,   0.0000000000,
                       0.0000000000,   0.0000000000,   1.0000000000
                  </Orientation>
                  <Position type="Vector">0, 0, 0</Position>
               </HpShieldCapacity05>
               <HpShieldCapacity06>
                  <Orientation type="Matrix">
                       1.0000000000,   0.0000000000,   0.0000000000,
                       0.0000000000,   1.0000000000,   0.0000000000,
                       0.0000000000,   0.0000000000,   1.0000000000
                  </Orientation>
                  <Position type="Vector">0, 0, 0</Position>
               </HpShieldCapacity06>
               <HpEngine01>
                  <Orientation type="Matrix">
                       1.0000000000,   0.0000000000,   0.0000000000,
                       0.0000000000,   1.0000000000,   0.0000000000,
                       0.0000000000,   0.0000000000,   1.0000000000
                  </Orientation>
                  <Position type="Vector">4.8008318, 2.4110141, 82.02121</Position>
               </HpEngine01>
               <HpEngine02>
                  <Orientation type="Matrix">
                       1.0000000000,   0.0000000000,   0.0000000000,
                       0.0000000000,   1.0000000000,   0.0000000000,
                       0.0000000000,   0.0000000000,   1.0000000000
                  </Orientation>
                  <Position type="Vector">-4.7772479, 2.4446211, 82.018417</Position>
               </HpEngine02>
               <HpDocklight01>
                  <Orientation type="Matrix">
                       1.0000000000,   0.0000000000,   0.0000000000,
                       0.0000000000,   1.0000000000,   0.0000000000,
                       0.0000000000,   0.0000000000,   1.0000000000
                  </Orientation>
                  <Position type="Vector">-24.905237, 21.541058, -11.364793</Position>
               </HpDocklight01>
               <HpDocklight02>
                  <Orientation type="Matrix">
                       1.0000000000,   0.0000000000,   0.0000000000,
                       0.0000000000,   1.0000000000,   0.0000000000,
                       0.0000000000,   0.0000000000,   1.0000000000
                  </Orientation>
                  <Position type="Vector">24.851404, 21.566832, -11.371566</Position>
               </HpDocklight02>
               <HpRunningLight01>
                  <Orientation type="Matrix">
                       1.0000000000,   0.0000000000,   0.0000000000,
                       0.0000000000,   1.0000000000,   0.0000000000,
                       0.0000000000,   0.0000000000,   1.0000000000
                  </Orientation>
                  <Position type="Vector">0, -13.753873, -132.40074</Position>
               </HpRunningLight01>
               <HpMine01>
                  <Orientation type="Matrix">
                       1.0000000000,   0.0000000000,   0.0000000000,
                       0.0000000000,   1.0000000000,   0.0000000000,
                       0.0000000000,   0.0000000000,   1.0000000000
                  </Orientation>
                  <Position type="Vector">0, 12.404958, 81.154671</Position>
               </HpMine01>
               <HpShield03>
                  <Orientation type="Matrix">
                       1.0000000000,   0.0000000000,   0.0000000000,
                       0.0000000000,   1.0000000000,   0.0000000000,
                       0.0000000000,   0.0000000000,   1.0000000000
                  </Orientation>
                  <Position type="Vector">0, 0, 0</Position>
               </HpShield03>
               <HpShieldCapacity07>
                  <Orientation type="Matrix">
                       1.0000000000,   0.0000000000,   0.0000000000,
                       0.0000000000,   1.0000000000,   0.0000000000,
                       0.0000000000,   0.0000000000,   1.0000000000
                  </Orientation>
                  <Position type="Vector">0, 0, 0</Position>
               </HpShieldCapacity07>
               <HpShieldGenerator07>
                  <Orientation type="Matrix">
                       1.0000000000,   0.0000000000,   0.0000000000,
                       0.0000000000,   1.0000000000,   0.0000000000,
                       0.0000000000,   0.0000000000,   1.0000000000
                  </Orientation>
                  <Position type="Vector">0, 0, 0</Position>
               </HpShieldGenerator07>
               <HpFX03>
                  <Orientation type="Matrix">
                      59.604645e-09,   0.9999998800,   0.0000000000,
                      -0.9999998800,  59.604645e-09,   0.0000000000,
                       0.0000000000,   0.0000000000,   1.0000000000
                  </Orientation>
                  <Position type="Vector">0, 0, 0</Position>
               </HpFX03>
               <HpFX04>
                  <Orientation type="Matrix">
                       1.0000000000,   0.0000000000,   0.0000000000,
                       0.0000000000,  59.604645e-09,   0.9999998800,
                       0.0000000000,  -0.9999998800,  59.604645e-09
                  </Orientation>
                  <Position type="Vector">0, 0, 0</Position>
               </HpFX04>
               <HpFX05>
                  <Orientation type="Matrix">
                       1.0000000000,   0.0000000000,   0.0000000000,
                       0.0000000000,   1.0000000000,   0.0000000000,
                       0.0000000000,   0.0000000000,   1.0000000000
                  </Orientation>
                  <Position type="Vector">0, 0, 0</Position>
               </HpFX05>
               <HpFX06>
                  <Orientation type="Matrix">
                       1.0000000000,   0.0000000000,   0.0000000000,
                       0.0000000000,   1.0000000000,   0.0000000000,
                       0.0000000000,   0.0000000000,   1.0000000000
                  </Orientation>
                  <Position type="Vector">0, 0, 0</Position>
               </HpFX06>
               <HpFX07>
                  <Orientation type="Matrix">
                       1.0000000000,   0.0000000000,   0.0000000000,
                       0.0000000000,   1.0000000000,   0.0000000000,
                       0.0000000000,   0.0000000000,   1.0000000000
                  </Orientation>
                  <Position type="Vector">0, 0, 0</Position>
               </HpFX07>
               <HpShield04>
                  <Orientation type="Matrix">
                       1.0000000000,   0.0000000000,   0.0000000000,
                       0.0000000000,   1.0000000000,   0.0000000000,
                       0.0000000000,   0.0000000000,   1.0000000000
                  </Orientation>
                  <Position type="Vector">0, 0, 0</Position>
               </HpShield04>
            </Fixed>
            <Revolute>
               <HpTorpedo01>
                  <Axis type="Vector">0, 1, 0</Axis>
                  <Max type="float">2.4434609</Max>
                  <Min type="float">-2.4434609</Min>
                  <Orientation type="Matrix">
                      -1.0000000000, -87.422777e-09,   0.0000000000,
                      87.422777e-09,  -1.0000000000,  -0.0000000000,
                       0.0000000000,   0.0000000000,   1.0000000000
                  </Orientation>
                  <Position type="Vector">0, -14.333491, -128.6819</Position>
               </HpTorpedo01>
               <HpLTurret01>
                  <Axis type="Vector">0, 1, 0</Axis>
                  <Max type="float">3.1415927</Max>
                  <Min type="float">-3.1415927</Min>
                  <Orientation type="Matrix">
                       0.9998476500,  29.103830e-12,  -0.0174524060,
                      913.38845e-06,   0.9986295100,   0.0523279870,
                       0.0174284890,  -0.0523359590,   0.9984774000
                  </Orientation>
                  <Position type="Vector">0, 30.364862, -1.904587</Position>
               </HpLTurret01>
               <HpLTurret02>
                  <Axis type="Vector">0, 1, 0</Axis>
                  <Max type="float">3.1415927</Max>
                  <Min type="float">-3.1415927</Min>
                  <Orientation type="Matrix">
                      -1.0000000000, -87.422777e-09,   0.0000000000,
                      87.422777e-09,  -1.0000000000,  -0.0000000000,
                       0.0000000000,   0.0000000000,   1.0000000000
                  </Orientation>
                  <Position type="Vector">0, -15.210066, -39.759659</Position>
               </HpLTurret02>
               <HpSTurret01>
                  <Axis type="Vector">0, 1, 0</Axis>
                  <Max type="float">3.1415927</Max>
                  <Min type="float">-3.1415927</Min>
                  <Orientation type="Matrix">
                       0.9135454300,  -0.4051889200,  -0.0354494380,
                       0.4067366700,   0.9100691100,   0.0796207410,
                       0.0000000000,  -0.0871557520,   0.9961946600
                  </Orientation>
                  <Position type="Vector">-11.566841, 24.679895, -46.954163</Position>
               </HpSTurret01>
               <HpSTurret02>
                  <Axis type="Vector">0, 1, 0</Axis>
                  <Max type="float">3.1415927</Max>
                  <Min type="float">-3.1415927</Min>
                  <Orientation type="Matrix">
                       0.9135454300,   0.4051889200,   0.0354494380,
                      -0.4067366700,   0.9100691100,   0.0796207410,
                       0.0000000000,  -0.0871557520,   0.9961946600
                  </Orientation>
                  <Position type="Vector">11.566841, 24.679895, -46.954163</Position>
               </HpSTurret02>
               <HpSTurret03>
                  <Axis type="Vector">0, 1, 0</Axis>
                  <Max type="float">3.1415927</Max>
                  <Min type="float">-3.1415927</Min>
                  <Orientation type="Matrix">
                      -1.0000000000, -87.422777e-09,   0.0000000000,
                      87.422777e-09,  -1.0000000000,  -0.0000000000,
                       0.0000000000,   0.0000000000,   1.0000000000
                  </Orientation>
                  <Position type="Vector">0, -15.181593, -43.741302</Position>
               </HpSTurret03>
               <HpSTurret04>
                  <Axis type="Vector">0, 1, 0</Axis>
                  <Max type="float">3.1415927</Max>
                  <Min type="float">-3.1415927</Min>
                  <Orientation type="Matrix">
                      -1.0000000000, -87.422777e-09,   0.0000000000,
                      87.422777e-09,  -1.0000000000,  -0.0000000000,
                       0.0000000000,   0.0000000000,   1.0000000000
                  </Orientation>
                  <Position type="Vector">0, -14.970922, -72.505821</Position>
               </HpSTurret04>
               <HpSTurret05>
                  <Axis type="Vector">0, 1, 0</Axis>
                  <Max type="float">3.1415927</Max>
                  <Min type="float">-3.1415927</Min>
                  <Orientation type="Matrix">
                       0.8829476200,  -0.4676850700,  -0.0409171430,
                       0.4694715400,   0.8795877100,   0.0769539550,
                     -1.8626451e-09,  -0.0871557370,   0.9961947200
                  </Orientation>
                  <Position type="Vector">-13.466803, 27.033541, -13.007766</Position>
               </HpSTurret05>
               <HpSTurret06>
                  <Axis type="Vector">0, 1, 0</Axis>
                  <Max type="float">3.1415927</Max>
                  <Min type="float">-3.1415927</Min>
                  <Orientation type="Matrix">
                       0.8829476200,   0.4676850700,   0.0409171430,
                      -0.4694715400,   0.8795877100,   0.0769539550,
                      1.8626451e-09,  -0.0871557370,   0.9961947200
                  </Orientation>
                  <Position type="Vector">13.38237, 27.073061, -13.032537</Position>
               </HpSTurret06>
               <HpSTurret07>
                  <Axis type="Vector">0, 1, 0</Axis>
                  <Max type="float">3.1415927</Max>
                  <Min type="float">-3.1415927</Min>
                  <Orientation type="Matrix">
                      -1.0000000000, -87.422777e-09,   0.0000000000,
                      87.422777e-09,  -1.0000000000,  -0.0000000000,
                       0.0000000000,   0.0000000000,   1.0000000000
                  </Orientation>
                  <Position type="Vector">-4.47967, -16.891222, -27.373495</Position>
               </HpSTurret07>
               <HpSTurret08>
                  <Axis type="Vector">0, 1, 0</Axis>
                  <Max type="float">3.1415927</Max>
                  <Min type="float">-3.1415927</Min>
                  <Orientation type="Matrix">
                      -1.0000000000, -87.422777e-09,   0.0000000000,
                      87.422777e-09,  -1.0000000000,  -0.0000000000,
                       0.0000000000,   0.0000000000,   1.0000000000
                  </Orientation>
                  <Position type="Vector">4.420063, -16.889399, -27.413033</Position>
               </HpSTurret08>
               <HpSTurret09>
                  <Axis type="Vector">0, 1, 0</Axis>
                  <Max type="float">3.1415927</Max>
                  <Min type="float">-3.1415927</Min>
                  <Orientation type="Matrix">
                       1.0000000000,   0.0000000000,   0.0000000000,
                       0.0000000000,   0.9961947200,   0.0871557440,
                       0.0000000000,  -0.0871557440,   0.9961947200
                  </Orientation>
                  <Position type="Vector">-5.0363932, 28.260212, -35.493877</Position>
               </HpSTurret09>
               <HpSTurret10>
                  <Axis type="Vector">0, 1, 0</Axis>
                  <Max type="float">3.1415927</Max>
                  <Min type="float">-3.1415927</Min>
                  <Orientation type="Matrix">
                       1.0000000000,   0.0000000000,   0.0000000000,
                       0.0000000000,   0.9961947200,   0.0871557440,
                       0.0000000000,  -0.0871557440,   0.9961947200
                  </Orientation>
                  <Position type="Vector">4.8756042, 28.267578, -35.485111</Position>
               </HpSTurret10>
               <HpSTurret11N>
                  <Axis type="Vector">0, 1, 0</Axis>
                  <Max type="float">1.6580628</Max>
                  <Min type="float">-1.6580628</Min>
                  <Orientation type="Matrix">
                      -0.0049946904,   0.1907436300,   0.9816272300,
                       0.0256960320,  -0.9812908800,   0.1908090000,
                       0.9996573900,   0.0261769440, -209.54758e-09
                  </Orientation>
                  <Position type="Vector">-107.7589, -29.015551, 71.500427</Position>
               </HpSTurret11N>
               <HpSTurret12N>
                  <Axis type="Vector">0, 1, 0</Axis>
                  <Max type="float">1.6580628</Max>
                  <Min type="float">-1.6580628</Min>
                  <Orientation type="Matrix">
                      -0.0049946904,  -0.1907436300,  -0.9816272300,
                      -0.0256960320,  -0.9812908800,   0.1908090000,
                      -0.9996573900,   0.0261769440, -209.54758e-09
                  </Orientation>
                  <Position type="Vector">107.7589, -29.015551, 71.500427</Position>
               </HpSTurret12N>
               <HpSTurret13N>
                  <Axis type="Vector">0, 1, 0</Axis>
                  <Max type="float">3.1415927</Max>
                  <Min type="float">-3.1415927</Min>
                  <Orientation type="Matrix">
                      -1.0000000000, -87.419451e-09, -762.89797e-12,
                      87.422777e-09,  -0.9999618500,  -0.0087265354,
                      27.755576e-18,  -0.0087265354,   0.9999619100
                  </Orientation>
                  <Position type="Vector">0, -15.068972, -59.036247</Position>
               </HpSTurret13N>
               <HpT01>
                  <Axis type="Vector">0, 1, 0</Axis>
                  <Max type="float">0</Max>
                  <Min type="float">0</Min>
                  <Orientation type="Matrix">
                       0.9659258100,  14.901161e-09,   0.2588190400,
                       0.2588190400,  7.4505806e-09,  -0.9659256900,
                       0.0000000000,   0.9999998800,  5.5879354e-09
                  </Orientation>
                  <Position type="Vector">-66.351227, -6.9070082, -26.049685</Position>
               </HpT01>
               <HpT02>
                  <Axis type="Vector">0, 1, 0</Axis>
                  <Max type="float">0</Max>
                  <Min type="float">0</Min>
                  <Orientation type="Matrix">
                       0.9659258100, -14.901161e-09,  -0.2588190400,
                      -0.2588190400,  7.4505806e-09,  -0.9659256900,
                       0.0000000000,   0.9999998800,  5.5879354e-09
                  </Orientation>
                  <Position type="Vector">66.830147, -7.0648642, -25.444843</Position>
               </HpT02>
               <HpSTurret11>
                  <Axis type="Vector">0, 1, 0</Axis>
                  <Max type="float">3.1415927</Max>
                  <Min type="float">-3.1415927</Min>
                  <Orientation type="Matrix">
                      -1.0000000000, -87.419451e-09, -762.89797e-12,
                      87.422777e-09,  -0.9999618500,  -0.0087265354,
                      27.755576e-18,  -0.0087265354,   0.9999619100
                  </Orientation>
                  <Position type="Vector">0, -15.223979, -37.878376</Position>
               </HpSTurret11>
               <HpSTurret12>
                  <Axis type="Vector">0, 1, 0</Axis>
                  <Max type="float">3.1415927</Max>
                  <Min type="float">-3.1415927</Min>
                  <Orientation type="Matrix">
                      -1.0000000000, -87.422777e-09,   0.0000000000,
                      87.422777e-09,  -1.0000000000,  -0.0000000000,
                       0.0000000000,   0.0000000000,   1.0000000000
                  </Orientation>
                  <Position type="Vector">0, -14.896793, -82.594193</Position>
               </HpSTurret12>
               <HpSTurret13>
                  <Axis type="Vector">0, 1, 0</Axis>
                  <Max type="float">3.1415927</Max>
                  <Min type="float">-3.1415927</Min>
                  <Orientation type="Matrix">
                       0.9998476500,  29.103830e-12,  -0.0174524060,
                      913.38845e-06,   0.9986295100,   0.0523279870,
                       0.0174284890,  -0.0523359590,   0.9984774000
                  </Orientation>
                  <Position type="Vector">0, 29.598621, -15.921745</Position>
               </HpSTurret13>
               <HpSTurret14>
                  <Axis type="Vector">0, 1, 0</Axis>
                  <Max type="float">3.1415927</Max>
                  <Min type="float">-3.1415927</Min>
                  <Orientation type="Matrix">
                      -1.0000000000, -87.422777e-09,   0.0000000000,
                      87.422777e-09,  -1.0000000000,  -0.0000000000,
                       0.0000000000,   0.0000000000,   1.0000000000
                  </Orientation>
                  <Position type="Vector">0, -14.942412, -76.568253</Position>
               </HpSTurret14>
            </Revolute>
         </Hardpoints>
         <MultiLevel>
            <Level0>
               <VMeshPart>
                  <VMeshRef type="VMeshRef">
                     <!-- header size  --> 60,
                     <!-- vmesh lib    --> Rebel_Galaxy_ship66.lod0.vms,
                     <!-- start vert   --> 0,
                     <!-- num verts    --> 4076,
                     <!-- start index  --> 0,
                     <!-- num indices  --> 12642,
                     <!-- start mesh   --> 0,
                     <!-- num meshes   --> 1,
                     <!-- bounding box -->  125.58614,   30.576138,    187.67665,
                                           -125.58614,  -30.576139,   -187.67665,
                     <!-- center       -->    0,       -953.67432e-9,    0,
                     <!-- radius       --> 284.85004
                  </VMeshRef>
               </VMeshPart>
            </Level0>
         </MultiLevel>
      </Rebel_Galaxy_ship66.3db>
   </UTF_ROOT>
</UTFXML>
